shelljob/__init__.py
shelljob/fs.py
shelljob/job.py
shelljob/proc.py
shelljob-0.6.2.dist-info/METADATA
shelljob-0.6.2.dist-info/WHEEL
shelljob-0.6.2.dist-info/top_level.txt
shelljob-0.6.2.dist-info/RECORD
