Metadata-Version: 2.1
Name: shelljob
Version: 0.6.2
Summary: Run multiple subprocesses asynchronous/in parallel with streamed output/non-blocking reading. Also various tools to replace shell scripts.
Home-page: https://github.com/mortoray/shelljob/
Author: edA-qa mort-ora-y
Author-email: eda-qa@disemia.com
License: GPLv3
Platform: UNKNOWN
Classifier: Development Status :: 6 - Mature
Classifier: Programming Language :: Python
Classifier: Programming Language :: Python :: 3
Classifier: Intended Audience :: Developers
Classifier: Environment :: Console
Classifier: License :: OSI Approved :: GNU General Public License v3 (GPLv3)
Classifier: Operating System :: OS Independent
Classifier: Topic :: Terminals
Classifier: Topic :: System
Classifier: Topic :: Software Development :: Build Tools
Requires-Python: >=3.6
